coveragePy/__init__.py
coveragePy/coverage_logger.py
coveragePy/flash.py
coveragePy/main.py
coveragePy/multiproc.py
coveragePy-1.6.0.dist-info/METADATA
coveragePy-1.6.0.dist-info/WHEEL
coveragePy-1.6.0.dist-info/entry_points.txt
coveragePy-1.6.0.dist-info/top_level.txt
coveragePy-1.6.0.dist-info/RECORD
