Metadata-Version: 2.1
Name: coveragePy
Version: 1.6.0
Summary: measure code coverage of Python programs 
Home-page: https://github.com/chexiedaping/coveragePy.git
Author: yapong.jia
Author-email: yapong.jia@huifu.com
License: GNU General Public License v3.0
Platform: UNKNOWN
Requires-Dist: flask (==1.0.2)
Requires-Dist: coverage (==4.5.3)
Requires-Dist: requests (==2.25.0)
